azurpaint/__init__.py
azurpaint/exception.py
azurpaint/main.py
azurpaint/types.py
azurpaint/classes/AABB.py
azurpaint/classes/AssetReader.py
azurpaint/classes/GameObject.py
azurpaint/classes/MeshImage.py
azurpaint/classes/RectTransform.py
azurpaint/classes/Vector2.py
azurpaint/classes/__init__.py
azurpaint-1.0.2.dist-info/licenses/LICENSE
azurpaint-1.0.2.dist-info/METADATA
azurpaint-1.0.2.dist-info/WHEEL
azurpaint-1.0.2.dist-info/top_level.txt
azurpaint-1.0.2.dist-info/RECORD
