Metadata-Version: 2.4
Name: azurpaint
Version: 1.0.2
Summary: Azur Lane painting reconstructor/extractor.
Author-email: Fernando <81207411+Fernando2603@users.noreply.github.com>
License: MIT License
Project-URL: Homepage, https://github.com/Fernando2603/azurpaint
Project-URL: Bug Tracker, https://github.com/Fernando2603/azurpaint/issues
Keywords: python,unity,azurlane,azur-lane,extractor
Classifier: License :: OSI Approved :: MIT License
Classifier: Operating System :: OS Independent
Classifier: Intended Audience :: Developers
Classifier: Programming Language :: Python
Classifier: Programming Language :: Python :: 3
Classifier: Programming Language :: Python :: 3.9
Classifier: Programming Language :: Python :: 3.10
Classifier: Programming Language :: Python :: 3.11
Classifier: Programming Language :: Python :: 3.12
Classifier: Topic :: Games/Entertainment
Classifier: Topic :: Multimedia :: Graphics
Requires-Python: >=3.9
License-File: LICENSE
Requires-Dist: Pillow
Requires-Dist: UnityPy==1.10.18
Dynamic: license-file
Dynamic: requires-python
